odoo/addons/report_xlsx_boilerplate/README.rst
odoo/addons/report_xlsx_boilerplate/__init__.py
odoo/addons/report_xlsx_boilerplate/__manifest__.py
odoo/addons/report_xlsx_boilerplate/i18n/report_xlsx_boilerplate.pot
odoo/addons/report_xlsx_boilerplate/readme/CONTRIBUTORS.rst
odoo/addons/report_xlsx_boilerplate/readme/DESCRIPTION.rst
odoo/addons/report_xlsx_boilerplate/readme/INSTALL.rst
odoo/addons/report_xlsx_boilerplate/readme/USAGE.rst
odoo/addons/report_xlsx_boilerplate/report/__init__.py
odoo/addons/report_xlsx_boilerplate/report/report_abstract_xlsx.py
odoo/addons/report_xlsx_boilerplate/report/utils/xlsx_utils.py
odoo/addons/report_xlsx_boilerplate/static/description/icon.png
odoo/addons/report_xlsx_boilerplate/static/description/index.html
odoo/addons/report_xlsx_boilerplate/tests/__init__.py
odoo/addons/report_xlsx_boilerplate/tests/test_report.py
odoo13_addon_report_xlsx_boilerplate-13.0.1.0.1.dev2.dist-info/METADATA
odoo13_addon_report_xlsx_boilerplate-13.0.1.0.1.dev2.dist-info/WHEEL
odoo13_addon_report_xlsx_boilerplate-13.0.1.0.1.dev2.dist-info/top_level.txt
odoo13_addon_report_xlsx_boilerplate-13.0.1.0.1.dev2.dist-info/RECORD
